{
    "name": "applets",
    "packages": [
        {
            "display_name": "Redshift",
            "name": "redshift",
            "installer": "pacman",
            "auto_start": [],
            "post_install_commands": [
                "systemctl enable --user --now redshift-gtk"
            ],
            "comments": [],
            "files": [
                {
                    "name": "redshift.conf",
                    "path_destination": "$HOME/.config",
                    "path_source": "$HOME/.dotfiles/redshift",
                    "text": "",
                    "create_link": true,
                    "sudo": false,
                    "comments": []
                }
            ]
        }
    ],
    "files": []
}